cex/__init__.py
cex/cex.py
python_cex-0.0.6.dist-info/METADATA
python_cex-0.0.6.dist-info/WHEEL
python_cex-0.0.6.dist-info/top_level.txt
python_cex-0.0.6.dist-info/RECORD
