Metadata-Version: 2.1
Name: python-cex
Version: 0.0.6
Summary: The Cleaning and EXploration kit for Data Scientist.
Author: John Willliam (Yande)
Author-email: <satwikayasayande@gmail.com>
Keywords: python,data science,cleaning,exploring,clean,explore
Classifier: Development Status :: 3 - Alpha
Classifier: Intended Audience :: Developers
Classifier: License :: OSI Approved :: GNU General Public License v3 (GPLv3)
Classifier: Programming Language :: Python :: 3
Classifier: Operating System :: Unix
Classifier: Operating System :: Microsoft :: Windows
Requires-Dist: pandas
Requires-Dist: numpy
Requires-Dist: matplotlib
Requires-Dist: scikit-learn
Requires-Dist: seaborn
Requires-Dist: scipy
